{
  "lastRoundupDate": "2026-05-14",
  "lastSpotlightSlugs": [
    "io-github-csoai-org-agent-handoff-certified-mcp",
    "io-github-wyre-technology-datto-saas-protection-mcp",
    "antigravity-workspace-template",
    "swatchbook-mcp",
    "e2eval",
    "vitemcp",
    "end-conversation-mcp-server-zh",
    "hermes-paperclip-adapter"
  ],
  "lastCategoryDeepDive": null,
  "lastCategoryDeepDiveDate": null,
  "lastSeoTopicIndex": -1,
  "publishedSeoTopics": [
    "MCP vs API what is the difference"
  ]
}